appezztp/__init__.py
appezztp/vtg_ezztp_inertia_register_tbm_.py
appezztp/z_core.py
appezztp/z_main.py
FridayZTP-0.9.7.dist-info/LICENSE.txt
FridayZTP-0.9.7.dist-info/METADATA
FridayZTP-0.9.7.dist-info/WHEEL
FridayZTP-0.9.7.dist-info/top_level.txt
FridayZTP-0.9.7.dist-info/RECORD
